microdatabase/__init__.py
microdatabase/_drivers.py
microdatabase/database.py
microdatabase-0.1.0.dist-info/licenses/LICENSE
microdatabase-0.1.0.dist-info/METADATA
microdatabase-0.1.0.dist-info/WHEEL
microdatabase-0.1.0.dist-info/top_level.txt
microdatabase-0.1.0.dist-info/RECORD
