Metadata-Version: 2.4
Name: microdatabase
Version: 0.1.0
Summary: Lightweight SQLite toolkit with schema enforcement, lambda queries, and row-level operations
Home-page: https://github.com/karl/microdatabase
Author: Karl Ehrlich
License: MIT
Classifier: Programming Language :: Python :: 3
Classifier: License :: OSI Approved :: MIT License
Classifier: Operating System :: OS Independent
Requires-Python: >=3.9
License-File: LICENSE
Dynamic: license-file
